archive/20251029_async_client.py
archive/20251029_batch_client.py
archive/20251030_prompt_extraction.py
gptquery/__init__.py
gptquery/core/__init__.py
gptquery/core/client.py
gptquery/core/execution_logger.py
gptquery/estimation/__init__.py
gptquery/estimation/cost_estimator.py
gptquery/estimation/prompt_generator.py
gptquery/estimation/tokens.py
gptquery/processing/__init__.py
gptquery/processing/throttling.py
gptquery/processing/utils.py
gptquery/tools/__init__.py
gptquery/tools/_templates/log.py
gptquery/tools/tool_eulaw_citations/__init__.py
gptquery/tools/tool_eulaw_citations/extract_citations/__init__.py
gptquery/tools/tool_eulaw_citations/extract_citations/log.py
gptquery/tools/tool_eulaw_citations/extract_citations/task.py
gptquery/tools/tool_eulaw_citations/extract_citations/prompts/__init__.py
gptquery/tools/tool_eulaw_citations/extract_citations/prompts/default.py
gptquery/tools/tool_eulaw_citations/select_citations/__init__.py
gptquery/tools/tool_eulaw_citations/select_citations/log.py
gptquery/tools/tool_eulaw_citations/select_citations/task.py
gptquery/tools/tool_eulaw_citations/select_citations/prompts/__init__.py
gptquery/tools/tool_eulaw_citations/select_citations/prompts/default.py
gptquery/tools/tool_eulaw_citations/select_citations/prompts/legacy_stdid.py
gptquery/tools/tool_eulaw_citations/validate_citations/__init__.py
gptquery/tools/tool_eulaw_citations/validate_citations/log.py
gptquery/tools/tool_eulaw_citations/validate_citations/task.py
gptquery/tools/tool_eulaw_citations/validate_citations/prompts/__init__.py
gptquery/tools/tool_eulaw_citations/validate_citations/prompts/default.py
gptquery/tools/tool_eulaw_citations/validate_citations/prompts/legacy_stdid.py
gptquery/tools/tool_text_extraction/__init__.py
gptquery/tools/tool_text_extraction/extract_affiliations/__init__.py
gptquery/tools/tool_text_extraction/extract_affiliations/log.py
gptquery/tools/tool_text_extraction/extract_affiliations/task.py
gptquerytools-0.0.1.dist-info/licenses/LICENSE
gptquerytools-0.0.1.dist-info/METADATA
gptquerytools-0.0.1.dist-info/WHEEL
gptquerytools-0.0.1.dist-info/top_level.txt
gptquerytools-0.0.1.dist-info/RECORD
