Metadata-Version: 2.4
Name: gptquerytools
Version: 0.0.1
Summary: GPTQuery is a modular Python framework for building, orchestrating, and deploying AI-powered tools across domains.
Author: Mauricio Mandujano Manriquez
License-Expression: MIT
Project-URL: Homepage, https://github.com/mauriciomm7/gptquery
Project-URL: Issues, https://github.com/mauriciomm7/gptquery/issues
Keywords: AI,tools,framework,research,GPT,modular
Requires-Python: >=3.10
License-File: LICENSE
Requires-Dist: pandas>=2.0
Requires-Dist: requests>=2.32
Requires-Dist: tokencost>=0.1.26
Requires-Dist: tiktoken>=0.12.0
Requires-Dist: IPython>=8.26.0
Dynamic: license-file
